{
  "id": "who_is_it_for",
  "label": "Who is it for",
  "repeatable": false,
  "json": {
    "Main": {
      "display_name": {
        "type": "StructuredText",
        "config": {
          "single": "heading1,heading2,heading3,heading4,heading5,heading6",
          "label": "Display Name"
        }
      },
      "uid": { "type": "UID", "config": { "label": "Slug" } },
      "body": {
        "type": "Slices",
        "fieldset": "Slice zone",
        "config": {
          "labels": { "intro": [], "is_right": [], "is_not_right": [] },
          "choices": {
            "ready_to_invest": {
              "type": "Slice",
              "fieldset": "Ready To Invest",
              "description": "Account opening teaser",
              "icon": "account_box",
              "display": "list",
              "non-repeat": {},
              "repeat": {}
            },
            "intro": {
              "type": "Slice",
              "fieldset": "Intro",
              "description": "Introduction text",
              "icon": "text_fields",
              "display": "list",
              "non-repeat": {
                "content": {
                  "type": "StructuredText",
                  "config": {
                    "multi": "paragraph,preformatted,heading1,heading2,heading3,heading4,heading5,heading6,strong,em,hyperlink,image,embed,list-item,o-list-item,rtl",
                    "label": "Content"
                  }
                }
              },
              "repeat": {}
            },
            "is_right": {
              "type": "Slice",
              "fieldset": "Is right",
              "description": "TW is right for you block",
              "icon": "check_circle",
              "display": "list",
              "non-repeat": {
                "title": { "type": "Text", "config": { "label": "Title" } },
                "image": {
                  "type": "Image",
                  "config": { "constraint": {}, "thumbnails": [], "label": "Image" }
                },
                "box_1": {
                  "type": "StructuredText",
                  "config": {
                    "multi": "paragraph,preformatted,heading1,heading2,heading3,heading4,heading5,heading6,strong,em,hyperlink,image,embed,list-item,o-list-item,rtl",
                    "label": "Box 1"
                  }
                },
                "box_2": {
                  "type": "StructuredText",
                  "config": {
                    "multi": "paragraph,preformatted,heading1,heading2,heading3,heading4,heading5,heading6,strong,em,hyperlink,image,embed,list-item,o-list-item,rtl",
                    "label": "Box 2"
                  }
                },
                "box_3": {
                  "type": "StructuredText",
                  "config": {
                    "multi": "paragraph,preformatted,heading1,heading2,heading3,heading4,heading5,heading6,strong,em,hyperlink,image,embed,list-item,o-list-item,rtl",
                    "label": "Box 3"
                  }
                },
                "box_4": {
                  "type": "StructuredText",
                  "config": {
                    "multi": "paragraph,preformatted,heading1,heading2,heading3,heading4,heading5,heading6,strong,em,hyperlink,image,embed,list-item,o-list-item,rtl",
                    "label": "Box 4"
                  }
                },
                "box_5": {
                  "type": "StructuredText",
                  "config": {
                    "multi": "paragraph,preformatted,heading1,heading2,heading3,heading4,heading5,heading6,strong,em,hyperlink,image,embed,list-item,o-list-item,rtl",
                    "label": "Box 5"
                  }
                }
              },
              "repeat": {}
            },
            "is_not_right": {
              "type": "Slice",
              "fieldset": "Is not right",
              "description": "TW is not right for you block",
              "icon": "cancel",
              "display": "list",
              "non-repeat": {
                "title": { "type": "Text", "config": { "label": "Title" } },
                "box_1": {
                  "type": "StructuredText",
                  "config": {
                    "multi": "paragraph,preformatted,heading1,heading2,heading3,heading4,heading5,heading6,strong,em,hyperlink,image,embed,list-item,o-list-item,rtl",
                    "label": "Box 1"
                  }
                },
                "box_2": {
                  "type": "StructuredText",
                  "config": {
                    "multi": "paragraph,preformatted,heading1,heading2,heading3,heading4,heading5,heading6,strong,em,hyperlink,image,embed,list-item,o-list-item,rtl",
                    "label": "Box 2"
                  }
                },
                "box_3": {
                  "type": "StructuredText",
                  "config": {
                    "multi": "paragraph,preformatted,heading1,heading2,heading3,heading4,heading5,heading6,strong,em,hyperlink,image,embed,list-item,o-list-item,rtl",
                    "label": "Box 3"
                  }
                },
                "box_4": {
                  "type": "StructuredText",
                  "config": {
                    "multi": "paragraph,preformatted,heading1,heading2,heading3,heading4,heading5,heading6,strong,em,hyperlink,image,embed,list-item,o-list-item,rtl",
                    "label": "Box 4"
                  }
                }
              },
              "repeat": {}
            }
          }
        }
      }
    },
    "SEO": {
      "seo_title": { "type": "Text", "config": { "label": "Title" } },
      "seo_description": { "type": "Text", "config": { "label": "Description" } },
      "social_media_image": {
        "type": "Image",
        "config": { "constraint": {}, "thumbnails": [], "label": "Social Media Image" }
      }
    },
    "Tracking": {
      "doubleclick_type": { "type": "Text", "config": { "label": "Doubleclick Type" } },
      "doubleclick_cat": { "type": "Text", "config": { "label": "Doubleclick Category" } }
    }
  },
  "hash": "a5d2b91bdb28e7b483f49d4795e2fd20",
  "status": true,
  "format": "custom"
}
